spotify_images/__init__.py
spotify_images/__main__.py
spotify_images/api.py
spotify_images/collage.py
spotify_images/config.py
spotify_images/images.py
spotify_album_art-0.0.3.1.dist-info/LICENSE
spotify_album_art-0.0.3.1.dist-info/METADATA
spotify_album_art-0.0.3.1.dist-info/WHEEL
spotify_album_art-0.0.3.1.dist-info/top_level.txt
spotify_album_art-0.0.3.1.dist-info/RECORD
