Metadata-Version: 2.1
Name: spotify-album-art
Version: 0.0.3.1
Summary: Download album artwork from Spotify
Home-page: https://github.com/orioncrocker/spotify_images
Author: Orion Crocker
Author-email: orion@orionc.dev
License: UNKNOWN
Platform: UNKNOWN
Classifier: Programming Language :: Python :: 3
Classifier: License :: OSI Approved :: MIT License
Classifier: Operating System :: OS Independent
Requires-Python: >=3.6
